CheckAndPick/CheckAndPick.py
CheckAndPick/__init__.py
CheckAndPick/__main__.py
CheckAndPick/config.py
CheckAndPick/generator.py
CheckAndPick/Workflow/SDXL_HighReso_I2I.json
CheckAndPick/Workflow/SDXL_HighReso_I2I_API.json
CheckAndPick/Workflow/SDXL_LoRA_LCM_Lightning.json
CheckAndPick/Workflow/SDXL_LoRA_LCM_Lightning_API.json
checkandpick-0.3.0.dist-info/METADATA
checkandpick-0.3.0.dist-info/WHEEL
checkandpick-0.3.0.dist-info/entry_points.txt
checkandpick-0.3.0.dist-info/licenses/LICENSE
checkandpick-0.3.0.dist-info/RECORD
