Metadata-Version: 2.4
Name: CheckAndPick
Version: 0.3.0
Summary: Image drafter.
Project-URL: Homepage, https://github.com/rerofumi/CheckAndPick
Author-email: rerofumi <rero2@yuumu.org>
License-File: LICENSE
Classifier: Development Status :: 3 - Alpha
Classifier: Intended Audience :: Developers
Classifier: License :: OSI Approved :: MIT License
Classifier: Operating System :: OS Independent
Classifier: Programming Language :: Python :: 3
Classifier: Topic :: Multimedia :: Graphics
Requires-Python: >=3.10
Requires-Dist: click>=8.1.8
Requires-Dist: fm-comfyui-bridge>=0.6.3
Requires-Dist: gradio>=5.9.1
Requires-Dist: pillow>=11.1.0
Requires-Dist: pyyaml>=6.0.2
